COPYING
MANIFEST.in
README
run_tests.sh
setup.cfg
setup.py
django_dumpdb/__init__.py
django_dumpdb/dumprestore.py
django_dumpdb.egg-info/PKG-INFO
django_dumpdb.egg-info/SOURCES.txt
django_dumpdb.egg-info/dependency_links.txt
django_dumpdb.egg-info/top_level.txt
testproject/__init__.py
testproject/manage.py
testproject/settings.py
testproject/urls.py
testproject/testmodels/__init__.py
testproject/testmodels/models.py
testproject/testmodels/tests.py
testproject/testmodels/views.py
testproject/testmodels/testdata/index
testproject/testmodels/testdata/cyclic_references/dump
testproject/testmodels/testdata/cyclic_references/dump.json
testproject/testmodels/testdata/empty/dump
testproject/testmodels/testdata/empty/dump.json
testproject/testmodels/testdata/simple/dump
testproject/testmodels/testdata/simple/dump.json