Metadata-Version: 1.0
Name: django-dumpdb
Version: 0.1
Summary: A better, faster, stronger alternative for manage.py dumpdata
Home-page: http://code.google.com/p/django-dumpdb/
Author: Andrey Golovizin
Author-email: golovizin@gmail.com
License: MIT
Platform: platform-independent
Classifier: Development Status :: 4 - Beta
Classifier: Operating System :: OS Independent
Classifier: License :: OSI Approved :: MIT License
Classifier: Intended Audience :: Developers
Classifier: Programming Language :: Python
Classifier: Environment :: Web Environment
Classifier: Framework :: Django
Classifier: Topic :: Utilities
